{"xml_msg": {"@query": "region=2,area=3,district=56,transaction=6", "supp_cb": null, "atms": {"atm": {"@id": "1447", "region": "Hong Kong", "area": "New Territories", "district": "Sham Tseng", "ob_name": "Bank of China (Hong Kong) Limited", "addr": "Shop G1& G2, Rhine Garden, Sham Tseng", "supp_tran": {"tran_name": ["Cash Withdrawal, Fund Transfer, Balance Enquiry, PIN Change and other basic services", "MPF", "Bill Payment, Credit Card Payment and Charity Donation", "PLUS", "JCB", "CUP", "CIRRUS", "FISC"]}, "currencies": {"currency": ["HKD", "RMB"]}, "latitude": "22.36815904750389", "longitude": "114.06104564666748"}}}}