{"xml_msg": {"@query": "region=2,area=2,district=21,transaction=5", "supp_cb": null, "atms": {"atm": [{"@id": "827", "region": "Hong Kong", "area": "Kowloon", "district": "Diamond Hill", "ob_name": "Standard Chartered Bank (Hong Kong) Limited", "addr": "Beside Shop 102, Level 1, Plaza Hollywood, Diamond Hill, Kowloon", "supp_tran": {"tran_name": ["Cash Withdrawal, Fund Transfer, Balance Enquiry, PIN Change and other basic services", "Bill Payment, Credit Card Payment and Charity Donation", "PLUS", "CUP", "CIRRUS"]}, "currencies": {"currency": ["HKD", "RMB"]}, "latitude": "22.3406515", "longitude": "114.2020839"}, {"@id": "822", "region": "Hong Kong", "area": "Kowloon", "district": "Diamond Hill", "ob_name": "Bank of China (Hong Kong) Limited", "addr": "(Opposite To Shop G146)Level 1,Plaza Hollywood, Diamond Hill, Kowloon.", "supp_tran": {"tran_name": ["Cash Withdrawal, Fund Transfer, Balance Enquiry, PIN Change and other basic services", "MPF", "Bill Payment, Credit Card Payment and Charity Donation", "PLUS", "JCB", "CUP", "CIRRUS", "FISC"]}, "currencies": {"currency": "HKD"}, "latitude": "22.34059915123745", "longitude": "114.20202255249023"}, {"@id": "823", "region": "Hong Kong", "area": "Kowloon", "district": "Diamond Hill", "ob_name": "Bank of China (Hong Kong) Limited", "addr": "(Opposite To Shop G146)Level 1,Plaza Hollywood, Diamond Hill, Kowloon.", "supp_tran": {"tran_name": ["Cash Withdrawal, Fund Transfer, Balance Enquiry, PIN Change and other basic services", "MPF", "Bill Payment, Credit Card Payment and Charity Donation", "PLUS", "JCB", "CUP", "CIRRUS", "FISC"]}, "currencies": {"currency": ["HKD", "RMB"]}, "latitude": "22.340509839383532", "longitude": "114.20208692550659"}, {"@id": "131687", "region": "Hong Kong", "area": "Kowloon", "district": "Diamond Hill", "ob_name": "Bank of China (Hong Kong) Limited", "addr": "G107 Plaza Hollywood, Diamond Hill, Kowloon", "supp_tran": {"tran_name": ["Cash Withdrawal, Fund Transfer, Balance Enquiry, PIN Change and other basic services", "MPF", "Bill Payment, Credit Card Payment and Charity Donation", "PLUS", "JCB", "CUP", "CIRRUS", "FISC"]}, "currencies": {"currency": ["HKD", "RMB"]}, "latitude": "22.3406515", "longitude": "114.2020839"}, {"@id": "824", "region": "Hong Kong", "area": "Kowloon", "district": "Diamond Hill", "ob_name": "Bank of China (Hong Kong) Limited", "addr": "MTR. Diamond Hill Station", "supp_tran": {"tran_name": ["Cash Withdrawal, Fund Transfer, Balance Enquiry, PIN Change and other basic services", "MPF", "Bill Payment, Credit Card Payment and Charity Donation", "PLUS", "JCB", "CUP", "CIRRUS", "FISC"]}, "currencies": {"currency": ["HKD", "RMB"]}, "latitude": "22.339864807628803", "longitude": "114.20099258422852"}, {"@id": "171363", "region": "Hong Kong", "area": "Kowloon", "district": "Diamond Hill", "ob_name": "Bank of China (Hong Kong) Limited", "addr": "ATM No. 2, 5/F, Tsz Wan Shan Shopping Centre, Tsz Lok Estate, 10 Wan Wah Street, Tsz Wan Shan, Kowloon, Hong Kong.", "supp_tran": {"tran_name": ["Cash Withdrawal, Fund Transfer, Balance Enquiry, PIN Change and other basic services", "MPF", "Bill Payment, Credit Card Payment and Charity Donation", "PLUS", "JCB", "CUP", "CIRRUS", "FISC"]}, "currencies": {"currency": ["HKD", "RMB"]}, "latitude": "22.347152923069963", "longitude": "114.19952451786048"}, {"@id": "825", "region": "Hong Kong", "area": "Kowloon", "district": "Diamond Hill", "ob_name": "Bank of China (Hong Kong) Limited", "addr": "MTR Diamond Hill Station", "supp_tran": {"tran_name": ["Cash Withdrawal, Fund Transfer, Balance Enquiry, PIN Change and other basic services", "MPF", "Bill Payment, Credit Card Payment and Charity Donation", "PLUS", "JCB", "CUP", "CIRRUS", "FISC"]}, "currencies": {"currency": ["HKD", "RMB"]}, "latitude": "22.339902021080377", "longitude": "114.20103013515472"}, {"@id": "222064", "region": "Hong Kong", "area": "Kowloon", "district": "Diamond Hill", "ob_name": "The Bank of East Asia, Limited", "addr": "Shop 102A, Level 1, Plaza Hollywood, 3 Lung Poon Street, Diamond Hill", "supp_tran": {"tran_name": ["Cash Withdrawal, Fund Transfer, Balance Enquiry, PIN Change and other basic services", "MPF", "Interbank Transfer", "Bill Payment, Credit Card Payment and Charity Donation", "PLUS", "JCB", "CUP", "CIRRUS", "Diners Club", "FISC", "Discover"]}, "currencies": {"currency": "HKD"}, "latitude": "22.340722", "longitude": "114.20229549999999"}, {"@id": "156031", "region": "Hong Kong", "area": "Kowloon", "district": "Diamond Hill", "ob_name": "Industrial and Commercial Bank of China (Asia) Limited", "addr": "2/F, Fung Tak Shopping Centre, Diamond Hill, Kowloon", "supp_tran": {"tran_name": ["Cash Withdrawal, Fund Transfer, Balance Enquiry, PIN Change and other basic services", "Interbank Transfer", "Bill Payment, Credit Card Payment and Charity Donation", "JCB", "CUP", "CIRRUS"]}, "currencies": {"currency": ["HKD", "RMB"]}, "latitude": "22.343866", "longitude": "114.19994759999997"}]}}}