{"xml_msg": {"@query": "region=2,area=1,district=2,transaction=5", "supp_cb": null, "atms": {"atm": [{"@id": "392", "region": "香港", "area": "香港", "district": "金鐘", "ob_name": "渣打銀行(香港)有限公司", "addr": "金鐘夏愨道16號遠東金融中心低層地下C舖", "supp_tran": {"tran_name": ["現金提款, 轉賬, 結餘查詢, 更改私人密碼及其他基本服務", "賬單繳費, 信用卡繳費, 慈善捐款", "PLUS", "銀聯", "CIRRUS"]}, "currencies": {"currency": ["港幣", "人民幣"]}, "latitude": "22.279997845717304", "longitude": "114.16424095630646"}, {"@id": "44189", "region": "香港", "area": "香港", "district": "金鐘", "ob_name": "中國銀行(香港)有限公司", "addr": "香港金鐘夏愨道18號海富中心一樓F97號舖", "supp_tran": {"tran_name": ["現金提款, 轉賬, 結餘查詢, 更改私人密碼及其他基本服務", "強積金", "賬單繳費, 信用卡繳費, 慈善捐款", "PLUS", "JCB", "銀聯", "CIRRUS", "FISC"]}, "currencies": {"currency": ["港幣", "人民幣"]}, "latitude": "22.279307858855177", "longitude": "114.16520118713379"}, {"@id": "44190", "region": "香港", "area": "香港", "district": "金鐘", "ob_name": "中國銀行(香港)有限公司", "addr": "香港金鐘夏愨道18號海富中心一樓F97號舖", "supp_tran": {"tran_name": ["現金提款, 轉賬, 結餘查詢, 更改私人密碼及其他基本服務", "強積金", "賬單繳費, 信用卡繳費, 慈善捐款", "PLUS", "JCB", "銀聯", "CIRRUS", "FISC"]}, "currencies": {"currency": "港幣"}, "latitude": "22.2793277146398", "longitude": "114.16519582271576"}, {"@id": "383", "region": "香港", "area": "香港", "district": "金鐘", "ob_name": "中國銀行(香港)有限公司", "addr": "金鐘港鐵站", "supp_tran": {"tran_name": ["現金提款, 轉賬, 結餘查詢, 更改私人密碼及其他基本服務", "強積金", "賬單繳費, 信用卡繳費, 慈善捐款", "PLUS", "JCB", "銀聯", "CIRRUS", "FISC"]}, "currencies": {"currency": ["港幣", "人民幣"]}, "latitude": "22.279089445038363", "longitude": "114.16548013687134"}, {"@id": "384", "region": "香港", "area": "香港", "district": "金鐘", "ob_name": "中國銀行(香港)有限公司", "addr": "香港金鐘道95號統一中心商場1021號", "supp_tran": {"tran_name": ["現金提款, 轉賬, 結餘查詢, 更改私人密碼及其他基本服務", "強積金", "賬單繳費, 信用卡繳費, 慈善捐款", "PLUS", "JCB", "銀聯", "CIRRUS", "FISC"]}, "currencies": {"currency": ["港幣", "人民幣"]}, "latitude": "22.27842427358582", "longitude": "114.16550159454346"}, {"@id": "382", "region": "香港", "area": "香港", "district": "金鐘", "ob_name": "東亞銀行有限公司", "addr": "金鐘金鐘道95號統一中心1007 & 1008號舖", "supp_tran": {"tran_name": ["現金提款, 轉賬, 結餘查詢, 更改私人密碼及其他基本服務", "強積金", "跨行轉賬", "賬單繳費, 信用卡繳費, 慈善捐款", "PLUS", "JCB", "銀聯", "CIRRUS", "Diners Club", "FISC", "Discover"]}, "currencies": {"currency": "港幣"}, "latitude": "22.27842427358582", "longitude": "114.16521191596985"}, {"@id": "231826", "region": "香港", "area": "香港", "district": "金鐘", "ob_name": "東亞銀行有限公司", "addr": "金鐘金鐘道95號統一中心1007 & 1008號舖", "supp_tran": {"tran_name": ["現金提款, 轉賬, 結餘查詢, 更改私人密碼及其他基本服務", "強積金", "跨行轉賬", "賬單繳費, 信用卡繳費, 慈善捐款", "PLUS", "JCB", "銀聯", "CIRRUS", "Diners Club", "FISC", "Discover"]}, "currencies": {"currency": ["港幣", "人民幣"]}, "latitude": "22.278373", "longitude": "114.165369"}, {"@id": "38698", "region": "香港", "area": "香港", "district": "金鐘", "ob_name": "東亞銀行有限公司", "addr": "金鐘添美道2號政府總部1樓A區", "supp_tran": {"tran_name": ["現金提款, 轉賬, 結餘查詢, 更改私人密碼及其他基本服務", "強積金", "跨行轉賬", "賬單繳費, 信用卡繳費, 慈善捐款", "PLUS", "JCB", "銀聯", "CIRRUS", "Diners Club", "FISC", "Discover"]}, "currencies": {"currency": ["港幣", "人民幣"]}, "latitude": "22.280330428096725", "longitude": "114.16558742523193"}, {"@id": "222066", "region": "香港", "area": "香港", "district": "金鐘", "ob_name": "東亞銀行有限公司", "addr": "金鐘金鐘道88號太古廣場3樓355號舖", "supp_tran": {"tran_name": ["現金提款, 轉賬, 結餘查詢, 更改私人密碼及其他基本服務", "強積金", "跨行轉賬", "賬單繳費, 信用卡繳費, 慈善捐款", "PLUS", "JCB", "銀聯", "CIRRUS", "Diners Club", "FISC", "Discover"]}, "currencies": {"currency": ["港幣", "人民幣"]}, "latitude": "22.2777138", "longitude": "114.16543509999997"}, {"@id": "222067", "region": "香港", "area": "香港", "district": "金鐘", "ob_name": "東亞銀行有限公司", "addr": "金鐘金鐘道88號太古廣場3樓355號舖", "supp_tran": {"tran_name": ["現金提款, 轉賬, 結餘查詢, 更改私人密碼及其他基本服務", "強積金", "跨行轉賬", "賬單繳費, 信用卡繳費, 慈善捐款", "PLUS", "JCB", "銀聯", "CIRRUS", "Diners Club", "FISC", "Discover"]}, "currencies": {"currency": "港幣"}, "latitude": "22.2777138", "longitude": "114.16543509999997"}, {"@id": "389", "region": "香港", "area": "香港", "district": "金鐘", "ob_name": "星展銀行(香港)有限公司", "addr": "金鐘金鐘道95號統一中心1樓", "supp_tran": {"tran_name": ["現金提款, 轉賬, 結餘查詢, 更改私人密碼及其他基本服務", "賬單繳費, 信用卡繳費, 慈善捐款", "PLUS", "銀聯", "CIRRUS"]}, "currencies": {"currency": ["港幣", "人民幣"]}, "latitude": "22.278592", "longitude": "114.165303"}, {"@id": "390", "region": "香港", "area": "香港", "district": "金鐘", "ob_name": "星展銀行(香港)有限公司", "addr": "金鐘金鐘道95號統一中心1樓", "supp_tran": {"tran_name": ["現金提款, 轉賬, 結餘查詢, 更改私人密碼及其他基本服務", "賬單繳費, 信用卡繳費, 慈善捐款", "PLUS", "銀聯", "CIRRUS"]}, "currencies": {"currency": ["港幣", "人民幣"]}, "latitude": "22.278592", "longitude": "114.165303"}, {"@id": "385", "region": "香港", "area": "香港", "district": "金鐘", "ob_name": "中信銀行(國際)有限公司", "addr": "金鐘金鐘道89號力寶中心", "supp_tran": {"tran_name": ["現金提款, 轉賬, 結餘查詢, 更改私人密碼及其他基本服務", "跨行轉賬", "賬單繳費, 信用卡繳費, 慈善捐款", "銀聯"]}, "currencies": {"currency": ["港幣", "人民幣"]}, "latitude": "22.279459", "longitude": "114.163343"}, {"@id": "386", "region": "香港", "area": "香港", "district": "金鐘", "ob_name": "中信銀行(國際)有限公司", "addr": "金鐘金鐘道89號力寶中心", "supp_tran": {"tran_name": ["現金提款, 轉賬, 結餘查詢, 更改私人密碼及其他基本服務", "跨行轉賬", "賬單繳費, 信用卡繳費, 慈善捐款", "銀聯"]}, "currencies": {"currency": ["港幣", "人民幣"]}, "latitude": "22.279459", "longitude": "114.163343"}, {"@id": "66153", "region": "香港", "area": "香港", "district": "金鐘", "ob_name": "中信銀行(國際)有限公司", "addr": "中環添美道1號中信大廈2樓202及207號舖", "supp_tran": {"tran_name": ["現金提款, 轉賬, 結餘查詢, 更改私人密碼及其他基本服務", "跨行轉賬", "賬單繳費, 信用卡繳費, 慈善捐款", "銀聯"]}, "currencies": {"currency": ["港幣", "人民幣"]}, "latitude": "22.280628262392035", "longitude": "114.16704654693604"}, {"@id": "80388", "region": "香港", "area": "香港", "district": "金鐘", "ob_name": "華僑永亨銀行有限公司", "addr": "金鐘金鐘道95號統一中心2樓2008-9號舖", "supp_tran": {"tran_name": ["現金提款, 轉賬, 結餘查詢, 更改私人密碼及其他基本服務", "強積金", "跨行轉賬", "賬單繳費, 信用卡繳費, 慈善捐款", "JCB", "銀聯"]}, "currencies": {"currency": "港幣"}, "latitude": "22.278578", "longitude": "114.165362"}, {"@id": "391", "region": "香港", "area": "香港", "district": "金鐘", "ob_name": "大新銀行有限公司", "addr": "金鐘夏愨道18號海富中心商場1樓10號舖", "supp_tran": {"tran_name": ["現金提款, 轉賬, 結餘查詢, 更改私人密碼及其他基本服務", "強積金", "跨行轉賬", "賬單繳費, 信用卡繳費, 慈善捐款", "PLUS", "銀聯", "CIRRUS"]}, "currencies": {"currency": "港幣"}, "latitude": "22.279387281976724", "longitude": "114.16494369506836"}, {"@id": "309240", "region": "香港", "area": "香港", "district": "金鐘", "ob_name": "中國工商銀行(亞洲)有限公司", "addr": "香港金鐘道95號統一中心1樓1019號舖", "supp_tran": {"tran_name": ["現金提款, 轉賬, 結餘查詢, 更改私人密碼及其他基本服務", "跨行轉賬", "賬單繳費, 信用卡繳費, 慈善捐款", "JCB", "銀聯", "CIRRUS"]}, "currencies": {"currency": ["港幣", "人民幣"]}, "latitude": "22.278571", "longitude": "114.165203"}, {"@id": "193413", "region": "香港", "area": "香港", "district": "金鐘", "ob_name": "花旗銀行(香港)有限公司", "addr": "香港金鐘金鐘道93號金鐘廊LAB Concept A13號舖", "supp_tran": {"tran_name": ["現金提款, 轉賬, 結餘查詢, 更改私人密碼及其他基本服務", "賬單繳費, 信用卡繳費, 慈善捐款", "PLUS", "銀聯", "CIRRUS"]}, "currencies": {"currency": ["港幣", "人民幣"]}, "latitude": "22.279395490484152", "longitude": "114.16459014484405"}, {"@id": "193412", "region": "香港", "area": "香港", "district": "金鐘", "ob_name": "花旗銀行(香港)有限公司", "addr": "香港金鐘金鐘道93號金鐘廊LAB Concept A13號舖", "supp_tran": {"tran_name": ["現金提款, 轉賬, 結餘查詢, 更改私人密碼及其他基本服務", "賬單繳費, 信用卡繳費, 慈善捐款", "PLUS", "銀聯", "CIRRUS"]}, "currencies": {"currency": ["港幣", "人民幣"]}, "latitude": "22.27937563470916", "longitude": "114.16460623809814"}]}}}