{"xml_msg": {"@query": "region=2,area=1,district=17,transaction=585", "supp_cb": null, "atms": {"atm": [{"@id": "711", "region": "香港", "area": "香港", "district": "灣仔", "ob_name": "東亞銀行有限公司", "addr": "灣仔軒尼詩道253至261號依時商業大厦地下A-C號", "supp_tran": {"tran_name": ["現金提款, 轉賬, 結餘查詢, 更改私人密碼及其他基本服務", "強積金", "跨行轉賬", "賬單繳費, 信用卡繳費, 慈善捐款", "PLUS", "JCB", "銀聯", "CIRRUS", "Diners Club", "FISC", "Discover"]}, "currencies": {"currency": ["港幣", "人民幣"]}, "latitude": "22.2780198", "longitude": "114.1763396"}, {"@id": "712", "region": "香港", "area": "香港", "district": "灣仔", "ob_name": "東亞銀行有限公司", "addr": "灣仔軒尼詩道253至261號依時商業大厦地下A-C號", "supp_tran": {"tran_name": ["現金提款, 轉賬, 結餘查詢, 更改私人密碼及其他基本服務", "強積金", "跨行轉賬", "賬單繳費, 信用卡繳費, 慈善捐款", "PLUS", "JCB", "銀聯", "CIRRUS", "Diners Club", "FISC", "Discover"]}, "currencies": {"currency": "港幣"}, "latitude": "22.2780198", "longitude": "114.1763396"}, {"@id": "168281", "region": "香港", "area": "香港", "district": "灣仔", "ob_name": "東亞銀行有限公司", "addr": "灣仔軒尼詩道253-261號依時商業大廈地下A-C號", "supp_tran": {"tran_name": ["現金提款, 轉賬, 結餘查詢, 更改私人密碼及其他基本服務", "強積金", "跨行轉賬", "賬單繳費, 信用卡繳費, 慈善捐款", "PLUS", "JCB", "銀聯", "CIRRUS", "Diners Club", "FISC", "Discover"]}, "currencies": {"currency": "港幣"}, "latitude": "22.27806425623526", "longitude": "114.17637896441806"}, {"@id": "713", "region": "香港", "area": "香港", "district": "灣仔", "ob_name": "東亞銀行有限公司", "addr": "灣仔軒尼詩道399號東區商業大廈地下", "supp_tran": {"tran_name": ["現金提款, 轉賬, 結餘查詢, 更改私人密碼及其他基本服務", "強積金", "跨行轉賬", "賬單繳費, 信用卡繳費, 慈善捐款", "PLUS", "JCB", "銀聯", "CIRRUS", "Diners Club", "FISC", "Discover"]}, "currencies": {"currency": "港幣"}, "latitude": "22.279124192713862", "longitude": "114.18028593063354"}, {"@id": "125593", "region": "香港", "area": "香港", "district": "灣仔", "ob_name": "東亞銀行有限公司", "addr": "灣仔軒尼詩道399號東區商業大廈地下", "supp_tran": {"tran_name": ["現金提款, 轉賬, 結餘查詢, 更改私人密碼及其他基本服務", "強積金", "跨行轉賬", "賬單繳費, 信用卡繳費, 慈善捐款", "PLUS", "JCB", "銀聯", "CIRRUS", "Diners Club", "FISC", "Discover"]}, "currencies": {"currency": "港幣"}, "latitude": "22.2791382", "longitude": "114.1804141"}, {"@id": "714", "region": "香港", "area": "香港", "district": "灣仔", "ob_name": "東亞銀行有限公司", "addr": "灣仔皇后大道東228號地下B及C舖", "supp_tran": {"tran_name": ["現金提款, 轉賬, 結餘查詢, 更改私人密碼及其他基本服務", "強積金", "跨行轉賬", "賬單繳費, 信用卡繳費, 慈善捐款", "PLUS", "JCB", "銀聯", "CIRRUS", "Diners Club", "FISC", "Discover"]}, "currencies": {"currency": "港幣"}, "latitude": "22.274584583997786", "longitude": "114.17294204235077"}, {"@id": "165188", "region": "香港", "area": "香港", "district": "灣仔", "ob_name": "東亞銀行有限公司", "addr": "灣仔皇后大道東228號地下B及C", "supp_tran": {"tran_name": ["現金提款, 轉賬, 結餘查詢, 更改私人密碼及其他基本服務", "強積金", "跨行轉賬", "賬單繳費, 信用卡繳費, 慈善捐款", "PLUS", "JCB", "銀聯", "CIRRUS", "Diners Club", "FISC", "Discover"]}, "currencies": {"currency": "港幣"}, "latitude": "22.274476686649762", "longitude": "114.17296899999996"}, {"@id": "715", "region": "香港", "area": "香港", "district": "灣仔", "ob_name": "東亞銀行有限公司", "addr": "灣仔告士打道56號東亞銀行港灣中心地下1號舖", "supp_tran": {"tran_name": ["現金提款, 轉賬, 結餘查詢, 更改私人密碼及其他基本服務", "強積金", "跨行轉賬", "賬單繳費, 信用卡繳費, 慈善捐款", "PLUS", "JCB", "銀聯", "CIRRUS", "Diners Club", "FISC", "Discover"]}, "currencies": {"currency": "港幣"}, "latitude": "22.279014985704666", "longitude": "114.17126566171646"}, {"@id": "251742", "region": "香港", "area": "香港", "district": "灣仔", "ob_name": "東亞銀行有限公司", "addr": "灣仔告士打道56號東亞銀行港灣中心地下1號", "supp_tran": {"tran_name": ["現金提款, 轉賬, 結餘查詢, 更改私人密碼及其他基本服務", "強積金", "跨行轉賬", "賬單繳費, 信用卡繳費, 慈善捐款", "PLUS", "JCB", "銀聯", "CIRRUS", "Diners Club", "FISC", "Discover"]}, "currencies": {"currency": ["港幣", "人民幣"]}, "latitude": "22.278869", "longitude": "114.171170"}, {"@id": "215666", "region": "香港", "area": "香港", "district": "灣仔", "ob_name": "東亞銀行有限公司", "addr": "灣仔港灣道1號會展廣場1樓101號舖", "supp_tran": {"tran_name": ["現金提款, 轉賬, 結餘查詢, 更改私人密碼及其他基本服務", "強積金", "跨行轉賬", "賬單繳費, 信用卡繳費, 慈善捐款", "PLUS", "JCB", "銀聯", "CIRRUS", "Diners Club", "FISC", "Discover"]}, "currencies": {"currency": ["港幣", "人民幣"]}, "latitude": "22.281125", "longitude": "114.17298359999995"}, {"@id": "717", "region": "香港", "area": "香港", "district": "灣仔", "ob_name": "東亞銀行有限公司", "addr": "灣仔海港中心一樓SC#1號舖", "supp_tran": {"tran_name": ["現金提款, 轉賬, 結餘查詢, 更改私人密碼及其他基本服務", "強積金", "跨行轉賬", "賬單繳費, 信用卡繳費, 慈善捐款", "PLUS", "JCB", "銀聯", "CIRRUS", "Diners Club", "FISC", "Discover"]}, "currencies": {"currency": "港幣"}, "latitude": "22.281076", "longitude": "114.175695"}]}}}